aio_geojson_vicemergency_incidents/__init__.py
aio_geojson_vicemergency_incidents/__version__.py
aio_geojson_vicemergency_incidents/consts.py
aio_geojson_vicemergency_incidents/feed.py
aio_geojson_vicemergency_incidents/feed_entry.py
aio_geojson_vicemergency_incidents/feed_manager.py
aio_geojson_vicemergency_incidents-0.7.dist-info/LICENSE
aio_geojson_vicemergency_incidents-0.7.dist-info/METADATA
aio_geojson_vicemergency_incidents-0.7.dist-info/WHEEL
aio_geojson_vicemergency_incidents-0.7.dist-info/top_level.txt
aio_geojson_vicemergency_incidents-0.7.dist-info/RECORD
