Metadata-Version: 2.1
Name: aio_geojson_vicemergency_incidents
Version: 0.7
Summary: An async GeoJSON client library for VIC Emergency Incidents.
Home-page: https://github.com/kuchel77/python-aio-geojson-vicemergency-incidents
Author: Mark Kuchel
Author-email: mark@kuchel.net
Classifier: Programming Language :: Python :: 3.6
Classifier: Programming Language :: Python :: 3.7
Classifier: Programming Language :: Python :: 3.8
Classifier: License :: OSI Approved :: Apache Software License
Classifier: Operating System :: OS Independent
License-File: LICENSE
Requires-Dist: aio-geojson-client >=0.13
Requires-Dist: aiohttp >=3.5.4
Requires-Dist: pytz >=2019.01
Requires-Dist: markdownify
